sqlite3_qt/__init__.py
sqlite3_qt/dbapi2.py
sqlite3_qt/qt_compat.py
sqlite3_qt-0.1.0.dist-info/LICENSE
sqlite3_qt-0.1.0.dist-info/METADATA
sqlite3_qt-0.1.0.dist-info/WHEEL
sqlite3_qt-0.1.0.dist-info/top_level.txt
sqlite3_qt-0.1.0.dist-info/RECORD
