Metadata-Version: 2.1
Name: sqlite3-qt
Version: 0.1.0
Summary: Drop-in Qt-based replacement for the sqlite3 module
License: GPL-3.0 License
Project-URL: Repository, https://github.com/tikuma-lsuhsc/python-sqlite3-qt
Keywords: sqlite3,Qt
Classifier: Development Status :: 4 - Beta
Classifier: License :: OSI Approved :: GNU General Public License v3 (GPLv3)
Classifier: Topic :: Database
Classifier: Programming Language :: Python :: 3.8
Classifier: Programming Language :: Python :: 3.9
Classifier: Programming Language :: Python :: 3.10
Classifier: Programming Language :: Python :: 3.11
Classifier: Programming Language :: Python :: 3.12
Requires-Python: >=3.8
License-File: LICENSE
Requires-Dist: packaging
Requires-Dist: typing-extensions
